builders_hut/__init__.py
builders_hut/__main__.py
builders_hut/cmd_interface.py
builders_hut/utils.py
builders_hut/setups/__init__.py
builders_hut/setups/all_writes.py
builders_hut/setups/base_setup.py
builders_hut/setups/db_setup.py
builders_hut/setups/env_setup.py
builders_hut/setups/file_writter.py
builders_hut/setups/files_setup.py
builders_hut/setups/git_setup.py
builders_hut/setups/structure_setup.py
builders_hut/setups/database/__init__.py
builders_hut/setups/database/factory.py
builders_hut/setups/file_contents/__init__.py
builders_hut/setups/file_contents/app_api.py
builders_hut/setups/file_contents/app_api_v1.py
builders_hut/setups/file_contents/app_core.py
builders_hut/setups/file_contents/app_database.py
builders_hut/setups/file_contents/app_main.py
builders_hut/setups/file_contents/app_model.py
builders_hut/setups/file_contents/app_repository.py
builders_hut/setups/file_contents/app_schema.py
builders_hut/setups/file_contents/app_services.py
builders_hut/setups/file_contents/app_templates.py
builders_hut/setups/file_contents/env_file.py
builders_hut/setups/file_contents/gitignore_file.py
builders_hut/setups/file_contents/migrations_env_file.py
builders_hut/setups/file_contents/run_file.py
builders_hut-0.4.3.dist-info/licenses/LICENSE.txt
hut/__init__.py
hut/__main__.py
builders_hut-0.4.3.dist-info/METADATA
builders_hut-0.4.3.dist-info/WHEEL
builders_hut-0.4.3.dist-info/entry_points.txt
builders_hut-0.4.3.dist-info/top_level.txt
builders_hut-0.4.3.dist-info/RECORD
