Metadata-Version: 2.4
Name: builders-hut
Version: 0.4.3
Summary: FastAPI Scaffolding Tool
Author-email: Arnab Gupta <arnabgupta84@gmail.com>
Maintainer-email: Arnab Gupta <arnabgupta84@gmail.com>
License-Expression: BSD-3-Clause
Project-URL: Homepage, https://github.com/Agsdovah95/builders-hut
Project-URL: Documentation, https://github.com/Agsdovah95/builders-hut/blob/main/README.md
Project-URL: Repository, https://github.com/Agsdovah95/builders-hut
Project-URL: Issues, https://github.com/Agsdovah95/builders-hut/issues
Project-URL: Changelog, https://github.com/Agsdovah95/builders-hut/blob/main/CHANGELOG.md
Keywords: fastapi,scaffolding,project,generator,boilerplate,template,skeleton,framework,tool,application,service,module,component,library,package
Classifier: Programming Language :: Python :: 3.13
Classifier: Programming Language :: Python :: Implementation :: CPython
Classifier: Intended Audience :: Developers
Classifier: Operating System :: POSIX :: Linux
Classifier: Operating System :: Microsoft :: Windows
Requires-Python: >=3.13
License-File: LICENSE.txt
Requires-Dist: build
Requires-Dist: twine
Requires-Dist: typer
Requires-Dist: tomlkit
Dynamic: license-file
